NearBeach/CODE_OF_CONDUCT.md
NearBeach/CONTRIBUTING.md
NearBeach/LICENSE
NearBeach/PULL_REQUEST_TEMPLATE.md
NearBeach/README.md
NearBeach/__init__.py
NearBeach/admin.py
NearBeach/apps.py
NearBeach/context_processors.py
NearBeach/event_hooks.py
NearBeach/forms.py
NearBeach/models.py
NearBeach/private_media.py
NearBeach/requirements.txt
NearBeach/urls.py
NearBeach/urls_api_v0.py
NearBeach/urls_two_factor.py
NearBeach/decorators/__init__.py
NearBeach/decorators/check_destination.py
NearBeach/decorators/check_user_permissions/__init__.py
NearBeach/decorators/check_user_permissions/admin_permissions.py
NearBeach/decorators/check_user_permissions/api_object_data_permissions_v0.py
NearBeach/decorators/check_user_permissions/api_permissions_v0.py
NearBeach/decorators/check_user_permissions/api_sprint_permissions_v0.py
NearBeach/decorators/check_user_permissions/customer_permissions.py
NearBeach/decorators/check_user_permissions/gantt_chart_permissions.py
NearBeach/decorators/check_user_permissions/object_permissions.py
NearBeach/decorators/check_user_permissions/organisation_permissions.py
NearBeach/decorators/check_user_permissions/permission_denied.py
NearBeach/decorators/check_user_permissions/schedule_object_permissions.py
NearBeach/decorators/check_user_permissions/sprint_permissions.py
NearBeach/decorators/check_user_permissions/partials/__init__.py
NearBeach/decorators/check_user_permissions/partials/change_task_permissions.py
NearBeach/decorators/check_user_permissions/partials/customer_permissions.py
NearBeach/decorators/check_user_permissions/partials/generic_permissions.py
NearBeach/decorators/check_user_permissions/partials/kanban_board_permissions.py
NearBeach/decorators/check_user_permissions/partials/kanban_card_permissions.py
NearBeach/decorators/check_user_permissions/partials/kanban_column_permissions.py
NearBeach/decorators/check_user_permissions/partials/kanban_level_permissions.py
nearbeach-0.31.106.dist-info/METADATA
nearbeach-0.31.106.dist-info/WHEEL
nearbeach-0.31.106.dist-info/licenses/LICENSE
nearbeach-0.31.106.dist-info/RECORD
