Metadata-Version: 2.4
Name: NearBeach
Version: 0.31.106
Summary: NearBeach - an open source project management tool
Project-URL: Homepage, https://nearbeach.org
Project-URL: Documentation, https://nearbeach.readthedocs.org
Project-URL: Repository, https://github.com/NearBeach/NearBeach.git
Project-URL: Bug Tracker, https://nearbeach.youtrack.cloud
Author-email: Luke Christopher Clarke <luke@nearbeach.org>
Maintainer-email: Luke Christopher Clarke <luke@nearbeach.org>
License: MIT License
License-File: LICENSE
Keywords: open source,project,project management,request for change,task
Classifier: Development Status :: 3 - Alpha
Classifier: License :: OSI Approved :: MIT License
Classifier: Operating System :: OS Independent
Classifier: Programming Language :: Python :: 3
Requires-Python: >=3.10
Requires-Dist: azure-identity
Requires-Dist: azure-storage-blob
Requires-Dist: boto3==1.35.99
Requires-Dist: django-otp
Requires-Dist: django-two-factor-auth
Requires-Dist: django-two-factor-auth[phonenumberslite]
Requires-Dist: django>=4.2.17
Requires-Dist: djangorestframework
Requires-Dist: drf-spectacular
Requires-Dist: drf-spectacular[sidecar]
Requires-Dist: pillow>=10.0.1
Requires-Dist: pip>=19.2
Requires-Dist: simplejson
Requires-Dist: urllib3
Provides-Extra: dev
Requires-Dist: bandit; extra == 'dev'
Requires-Dist: black; extra == 'dev'
Requires-Dist: django-storages; extra == 'dev'
Requires-Dist: python-dotenv; extra == 'dev'
